event_delegate/__init__.py
event_delegate-1.0.0.dist-info/LICENSE
event_delegate-1.0.0.dist-info/METADATA
event_delegate-1.0.0.dist-info/WHEEL
event_delegate-1.0.0.dist-info/top_level.txt
event_delegate-1.0.0.dist-info/RECORD
