Metadata-Version: 2.1
Name: event-delegate
Version: 1.0.0
Summary: An event class for python.
Author-email: adorjanw <adorjanw@outlook.com>
Project-URL: Homepage, https://github.com/adorjanw/event-delegate-python
Classifier: Programming Language :: Python :: 3
Classifier: License :: OSI Approved :: MIT License
Classifier: Operating System :: OS Independent
Classifier: Topic :: Software Development :: Libraries
Requires-Python: >=3.7
License-File: LICENSE
